[{"name":"gl_MaxClipDistances","type":"int","placeP":true,"versions":["150","330","400","410","420","430","440","450","460","150Core","330Core","400Core","410Core","420Core","430Core","440Core","450Core","460Core"],"requirements":null},
{"name":"gl_MaxDrawBuffers","type":"int","placeP":true,"versions":["150","330","400","410","420","430","440","450","460","150Core","330Core","400Core","410Core","420Core","430Core","440Core","450Core","460Core"],"requirements":null},
{"name":"gl_MaxTextureUnits","type":"int","placeP":true,"versions":["150","330","400","410","420","430","440","450","460","150Core","330Core","400Core","410Core","420Core","430Core","440Core","450Core","460Core"],"requirements":null},
{"name":"gl_MaxGeometryTextureImageUnits","type":"int","placeP":true,"versions":["150","330","400","410","420","430","440","450","460","150Core","330Core","400Core","410Core","420Core","430Core","440Core","450Core","460Core"],"requirements":null},
{"name":"gl_MaxTextureImageUnits","type":"int","placeP":true,"versions":["150","330","400","410","420","430","440","450","460","150Core","330Core","400Core","410Core","420Core","430Core","440Core","450Core","460Core"],"requirements":null},
{"name":"gl_MaxVertexAttribs","type":"int","placeP":true,"versions":["150","330","400","410","420","430","440","450","460","150Core","330Core","400Core","410Core","420Core","430Core","440Core","450Core","460Core"],"requirements":null},
{"name":"gl_MaxVertexTextureImageUnits","type":"int","placeP":true,"versions":["150","330","400","410","420","430","440","450","460","150Core","330Core","400Core","410Core","420Core","430Core","440Core","450Core","460Core"],"requirements":null},
{"name":"gl_MaxCombinedTextureImageUnits","type":"int","placeP":true,"versions":["150","330","400","410","420","430","440","450","460","150Core","330Core","400Core","410Core","420Core","430Core","440Core","450Core","460Core"],"requirements":null},
{"name":"gl_MaxGeometryVaryingComponents","type":"int","placeP":true,"versions":["150","330","400","410","420","430","440","450","460","150Core","330Core","400Core","410Core","420Core","430Core","440Core","450Core","460Core"],"requirements":null},
{"name":"gl_MaxVaryingFloats","type":"int","placeP":true,"versions":["150","330","400","410","420","430","440","450","460","150Core","330Core","400Core","410Core","420Core","430Core","440Core","450Core","460Core"],"requirements":null},
{"name":"gl_MaxGeometryOutputVertices","type":"int","placeP":true,"versions":["150","330","400","410","420","430","440","450","460","150Core","330Core","400Core","410Core","420Core","430Core","440Core","450Core","460Core"],"requirements":null},
{"name":"gl_MaxFragmentUniformComponents","type":"int","placeP":true,"versions":["150","330","400","410","420","430","440","450","460","150Core","330Core","400Core","410Core","420Core","430Core","440Core","450Core","460Core"],"requirements":null},
{"name":"gl_MaxGeometryTotalOutputComponents","type":"int","placeP":true,"versions":["150","330","400","410","420","430","440","450","460","150Core","330Core","400Core","410Core","420Core","430Core","440Core","450Core","460Core"],"requirements":null},
{"name":"gl_MaxGeometryUniformComponents","type":"int","placeP":true,"versions":["150","330","400","410","420","430","440","450","460","150Core","330Core","400Core","410Core","420Core","430Core","440Core","450Core","460Core"],"requirements":null},
{"name":"gl_MaxVertexUniformComponents","type":"int","placeP":true,"versions":["150","330","400","410","420","430","440","450","460","150Core","330Core","400Core","410Core","420Core","430Core","440Core","450Core","460Core"],"requirements":null},
{"name":"gl_RayFlagsNoneEXT","type":"uint","placeP":true,"versions":["460","460Core"],"requirements":["vulkan","GL_EXT_ray_query"]},
{"name":"gl_RayFlagsOpaqueEXT","type":"uint","placeP":true,"versions":["460","460Core"],"requirements":["vulkan","GL_EXT_ray_query"]},
{"name":"gl_RayFlagsNoOpaqueEXT","type":"uint","placeP":true,"versions":["460","460Core"],"requirements":["vulkan","GL_EXT_ray_query"]},
{"name":"gl_RayFlagsTerminateOnFirstHitEXT","type":"uint","placeP":true,"versions":["460","460Core"],"requirements":["vulkan","GL_EXT_ray_query"]},
{"name":"gl_RayFlagsSkipClosestHitShaderEXT","type":"uint","placeP":true,"versions":["460","460Core"],"requirements":["vulkan","GL_EXT_ray_query"]},
{"name":"gl_RayFlagsCullBackFacingTrianglesEXT","type":"uint","placeP":true,"versions":["460","460Core"],"requirements":["vulkan","GL_EXT_ray_query"]},
{"name":"gl_RayFlagsCullFrontFacingTrianglesEXT","type":"uint","placeP":true,"versions":["460","460Core"],"requirements":["vulkan","GL_EXT_ray_query"]},
{"name":"gl_RayFlagsCullOpaqueEXT","type":"uint","placeP":true,"versions":["460","460Core"],"requirements":["vulkan","GL_EXT_ray_query"]},
{"name":"gl_RayFlagsCullNoOpaqueEXT","type":"uint","placeP":true,"versions":["460","460Core"],"requirements":["vulkan","GL_EXT_ray_query"]},
{"name":"gl_RayQueryCandidateIntersectionTriangleEXT","type":"uint","placeP":true,"versions":["460","460Core"],"requirements":["vulkan","GL_EXT_ray_query"]},
{"name":"gl_RayQueryCandidateIntersectionAABBEXT","type":"uint","placeP":true,"versions":["460","460Core"],"requirements":["vulkan","GL_EXT_ray_query"]},
{"name":"gl_RayQueryCommittedIntersectionNoneEXT","type":"uint","placeP":true,"versions":["460","460Core"],"requirements":["vulkan","GL_EXT_ray_query"]},
{"name":"gl_RayQueryCommittedIntersectionTriangleEXT","type":"uint","placeP":true,"versions":["460","460Core"],"requirements":["vulkan","GL_EXT_ray_query"]},
{"name":"gl_RayQueryCommittedIntersectionGeneratedEXT","type":"uint","placeP":true,"versions":["460","460Core"],"requirements":["vulkan","GL_EXT_ray_query"]},
{"name":"gl_InstanceID","type":"int","placeP":true,"versions":["140","150","330","400","410","420","430","440","450","460","140Core","150Core","330Core","400Core","410Core","420Core","430Core","440Core","450Core","460Core"],"stage":"vertex","requirements":["opengl"]},
{"name":"gl_InstanceIndex","type":"int","placeP":true,"versions":["140Core","150Core","330Core","400Core","410Core","420Core","430Core","440Core","450Core","460Core"],"stage":"vertex","requirements":["vulkan"]},
{"name":"gl_ClipDistance","type":"[float","placeP":null,"versions":["130","140","150","330","400","410","420","430","440","450","460","130Core","140Core","150Core","330Core","400Core","410Core","420Core","430Core","440Core","450Core","460Core"],"stage":"vertex","requirements":null},
{"name":"gl_PrimitiveIDIn","type":"int","placeP":true,"versions":["150","330","400","410","420","430","440","450","460","150Core","330Core","400Core","410Core","420Core","430Core","440Core","450Core","460Core"],"stage":"geometry","requirements":null},
{"name":"gl_ClipDistance","type":"[float","placeP":null,"versions":["130","140","150","330","400","410","420","430","440","450","460","130Core","140Core","150Core","330Core","400Core","410Core","420Core","430Core","440Core","450Core","460Core"],"stage":"geometry","requirements":null},
{"name":"gl_PrimitiveID","type":"int","placeP":null,"versions":["150","330","400","410","420","430","440","450","460","150Core","330Core","400Core","410Core","420Core","430Core","440Core","450Core","460Core"],"stage":"geometry","requirements":null},
{"name":"gl_FragCoord","type":"vec4","placeP":null,"versions":["110","120","130","140","150","330","400","410","420","430","440","450","460","130Core","140Core","150Core","330Core","400Core","410Core","420Core","430Core","440Core","450Core","460Core"],"stage":"fragment","requirements":null},
{"name":"gl_FrontFacing","type":"bool","placeP":true,"versions":["110","120","130","140","150","330","400","410","420","430","440","450","460","130Core","140Core","150Core","330Core","400Core","410Core","420Core","430Core","440Core","450Core","460Core"],"stage":"fragment","requirements":null},
{"name":"gl_ClipDistance","type":"[float","placeP":true,"versions":["130","140","150","330","400","410","420","430","440","450","460","130Core","140Core","150Core","330Core","400Core","410Core","420Core","430Core","440Core","450Core","460Core"],"stage":"fragment","requirements":null},
{"name":"gl_PrimitiveID","type":"int","placeP":true,"versions":["150","330","400","410","420","430","440","450","460","150Core","330Core","400Core","410Core","420Core","430Core","440Core","450Core","460Core"],"stage":"fragment","requirements":null},
{"name":"gl_FragData","type":"[vec4","placeP":true,"versions":["150","330","400","410","420","430","440","450","460","150Core","330Core","400Core","410Core","420Core","430Core","440Core","450Core","460Core"],"stage":"fragment","requirements":null},
{"name":"gl_FragDepth","type":"float","placeP":true,"versions":["110","120","130","140","150","330","400","410","420","430","440","450","460","130Core","140Core","150Core","330Core","400Core","410Core","420Core","430Core","440Core","450Core","460Core"],"stage":"fragment","requirements":null},
{"name":"gl_DepthRange","type":"gl_DepthRangeParameters","placeP":null,"versions":["150","330","400","410","420","430","440","450","460","150Core","330Core","400Core","410Core","420Core","430Core","440Core","450Core","460Core"],"stage":"fragment","requirements":["opengl"]},
{"name":"gl_ViewportIndex","type":"int","placeP":null,"versions":["150","330","400","410","420","430","440","450","460","150Core","330Core","400Core","410Core","420Core","430Core","440Core","450Core","460Core"],"stage":"geometry","requirements":null},
{"name":"gl_ViewportIndex","type":"int","placeP":null,"versions":["430","440","450","460","430Core","440Core","450Core","460Core"],"stage":"fragment","requirements":null},
{"name":"gl_PrimitiveID","type":"int","placeP":true,"versions":["400","410","420","430","440","450","460","400Core","410Core","420Core","430Core","440Core","450Core","460Core"],"stage":"tessellationControl","requirements":null},
{"name":"gl_PrimitiveID","type":"int","placeP":true,"versions":["400","410","420","430","440","450","460","400Core","410Core","420Core","430Core","440Core","450Core","460Core"],"stage":"tessellationEvaluation","requirements":null},
{"name":"gl_Layer","type":"int","placeP":null,"versions":["150","330","400","410","420","430","440","450","460","150Core","330Core","400Core","410Core","420Core","430Core","440Core","450Core","460Core"],"stage":"geometry","requirements":null},
{"name":"gl_Layer","type":"int","placeP":null,"versions":["430","440","450","460","430Core","440Core","450Core","460Core"],"stage":"fragment","requirements":null},
{"name":"gl_Position","type":"vec4","placeP":true,"versions":["110","120","130","140","150","330","400","410","420","430","440","450","460","130Core","140Core","150Core","330Core","400Core","410Core","420Core","430Core","440Core","450Core","460Core"],"stage":"vertex","requirements":null},
{"name":"gl_Position","type":"vec4","placeP":true,"versions":["110","120","130","140","150","330","400","410","420","430","440","450","460","130Core","140Core","150Core","330Core","400Core","410Core","420Core","430Core","440Core","450Core","460Core"],"stage":"geometry","requirements":null},
{"name":"gl_Position","type":"vec4","placeP":true,"versions":["110","120","130","140","150","330","400","410","420","430","440","450","460","130Core","140Core","150Core","330Core","400Core","410Core","420Core","430Core","440Core","450Core","460Core"],"stage":"tessellationEvaluation","requirements":null},
{"name":"gl_GlobalInvocationID","type":"uvec3","placeP":null,"versions":["430","440","450","460","430Core","440Core","450Core","460Core"],"stage":"compute","requirements":null},
{"name":"gl_HelperInvocation","type":"bool","placeP":null,"versions":["450","460","450Core","460Core"],"requirements":null},
{"name":"gl_InvocationID","type":"int","placeP":null,"versions":["150","330","400","410","420","430","440","450","460","150Core","330Core","400Core","410Core","420Core","430Core","440Core","450Core","460Core"],"stage":"geometry","requirements":null},
{"name":"gl_InvocationID","type":"int","placeP":null,"versions":["150","330","400","410","420","430","440","450","460","150Core","330Core","400Core","410Core","420Core","430Core","440Core","450Core","460Core"],"stage":"tessellationControl","requirements":null},
{"name":"gl_LocalInvocationID","type":"uvec3","placeP":null,"versions":["430","440","450","460","430Core","440Core","450Core","460Core"],"stage":"compute","requirements":null},
{"name":"gl_LocalInvocationIndex","type":"uint","placeP":null,"versions":["430","440","450","460","430Core","440Core","450Core","460Core"],"stage":"compute","requirements":null},
{"name":"gl_NumSamples","type":"bool","placeP":null,"versions":["400","410","420","430","440","450","460","400Core","410Core","420Core","430Core","440Core","450Core","460Core"],"requirements":["opengl"]},
{"name":"gl_NumWorkGroups","type":"uvec3","placeP":null,"versions":["430","440","450","460","430Core","440Core","450Core","460Core"],"stage":"compute","requirements":null},
{"name":"gl_PatchVerticesIn","type":"int","placeP":null,"versions":["400","410","420","430","440","450","460","400Core","410Core","420Core","430Core","440Core","450Core","460Core"],"requirements":null},
{"name":"gl_SampleID","type":"int","placeP":null,"versions":["400","410","420","430","440","450","460","400Core","410Core","420Core","430Core","440Core","450Core","460Core"],"requirements":null},
{"name":"gl_SampleMask","type":"int","placeP":null,"versions":["400","410","420","430","440","450","460","400Core","410Core","420Core","430Core","440Core","450Core","460Core"],"requirements":null},
{"name":"gl_SampleMaskIn","type":"int","placeP":null,"versions":["400","410","420","430","440","450","460","400Core","410Core","420Core","430Core","440Core","450Core","460Core"],"requirements":null},
{"name":"gl_SamplePosition","type":"vec2","placeP":null,"versions":["400","410","420","430","440","450","460","400Core","410Core","420Core","430Core","440Core","450Core","460Core"],"requirements":null},
{"name":"gl_TessCoord","type":"vec3","placeP":null,"versions":["400","410","420","430","440","450","460","400Core","410Core","420Core","430Core","440Core","450Core","460Core"],"requirements":null},
{"name":"gl_TessLevelInner","type":"[float","placeP":true,"versions":["400","410","420","430","440","450","460","400Core","410Core","420Core","430Core","440Core","450Core","460Core"],"requirements":null},
{"name":"gl_TessLevelOuter","type":"[float","placeP":true,"versions":["400","410","420","430","440","450","460","400Core","410Core","420Core","430Core","440Core","450Core","460Core"],"requirements":null},
{"name":"gl_WorkGroupID","type":"uvec3","placeP":null,"versions":["430","440","450","460","430Core","440Core","450Core","460Core"],"stage":"compute","requirements":null},
{"name":"gl_WorkGroupSize","type":"uvec3","placeP":null,"versions":["430","440","450","460","430Core","440Core","450Core","460Core"],"stage":"compute","requirements":null},
{"name":"gl_DrawID","type":"int","placeP":null,"versions":["460","460Core"],"stage":"vertex","requirements":null},
{"name":"gl_BaseVertex","type":"int","placeP":null,"versions":["460","460Core"],"stage":"vertex","requirements":null},
{"name":"gl_BaseInstance","type":"int","placeP":null,"versions":["460","460Core"],"stage":"vertex","requirements":null},
{"name":"gl_MaxClipPlanes","type":"int","placeP":true,"versions":["130","140","150","330","400","410","420","430","440","450","460","130Core"],"requirements":null},
{"name":"gl_MaxTextureCoords","type":"int","placeP":true,"versions":["130","140","150","330","400","410","420","430","440","450","460","130Core"],"requirements":null},
{"name":"gl_VertexID","type":"int","placeP":true,"versions":["130","140","150","330","400","410","420","430","440","450","460","130Core"],"stage":"vertex","requirements":["opengl"]},
{"name":"gl_VertexIndex","type":"int","placeP":true,"versions":["140Core","150Core","330Core","400Core","410Core","420Core","430Core","440Core","450Core","460Core"],"stage":"vertex","requirements":["vulkan"]},
{"name":"gl_Color","type":"vec4","placeP":true,"versions":["130","140","150","330","400","410","420","430","440","450","460","130Core"],"stage":"vertex","requirements":null},
{"name":"gl_SecondaryColor","type":"vec4","placeP":true,"versions":["130","140","150","330","400","410","420","430","440","450","460","130Core"],"stage":"vertex","requirements":null},
{"name":"gl_Normal","type":"vec3","placeP":true,"versions":["130","140","150","330","400","410","420","430","440","450","460","130Core"],"stage":"vertex","requirements":null},
{"name":"gl_Vertex","type":"vec4","placeP":true,"versions":["130","140","150","330","400","410","420","430","440","450","460","130Core"],"stage":"vertex","requirements":null},
{"name":"gl_MultiTexCoord0","type":"vec4","placeP":true,"versions":["130","140","150","330","400","410","420","430","440","450","460","130Core"],"stage":"vertex","requirements":null},
{"name":"gl_MultiTexCoord1","type":"vec4","placeP":true,"versions":["130","140","150","330","400","410","420","430","440","450","460","130Core"],"stage":"vertex","requirements":null},
{"name":"gl_MultiTexCoord2","type":"vec4","placeP":true,"versions":["130","140","150","330","400","410","420","430","440","450","460","130Core"],"stage":"vertex","requirements":null},
{"name":"gl_MultiTexCoord3","type":"vec4","placeP":true,"versions":["130","140","150","330","400","410","420","430","440","450","460","130Core"],"stage":"vertex","requirements":null},
{"name":"gl_MultiTexCoord4","type":"vec4","placeP":true,"versions":["130","140","150","330","400","410","420","430","440","450","460","130Core"],"stage":"vertex","requirements":null},
{"name":"gl_MultiTexCoord5","type":"vec4","placeP":true,"versions":["130","140","150","330","400","410","420","430","440","450","460","130Core"],"stage":"vertex","requirements":null},
{"name":"gl_MultiTexCoord6","type":"vec4","placeP":true,"versions":["130","140","150","330","400","410","420","430","440","450","460","130Core"],"stage":"vertex","requirements":null},
{"name":"gl_MultiTexCoord7","type":"vec4","placeP":true,"versions":["130","140","150","330","400","410","420","430","440","450","460","130Core"],"stage":"vertex","requirements":null},
{"name":"gl_FogCoord","type":"float","placeP":true,"versions":["130","140","150","330","400","410","420","430","440","450","460","130Core"],"stage":"vertex","requirements":null},
{"name":"gl_ClipVertex","type":"vec4","placeP":null,"versions":["130","140","150","330","400","410","420","430","440","450","460","130Core"],"stage":"vertex","requirements":null},
{"name":"gl_FrontColor","type":"vec4","placeP":null,"versions":["130","140","150","330","400","410","420","430","440","450","460","130Core"],"stage":"vertex","requirements":null},
{"name":"gl_BackColor","type":"vec4","placeP":null,"versions":["130","140","150","330","400","410","420","430","440","450","460","130Core"],"stage":"vertex","requirements":null},
{"name":"gl_FrontSecondaryColor","type":"vec4","placeP":null,"versions":["130","140","150","330","400","410","420","430","440","450","460","130Core"],"stage":"vertex","requirements":null},
{"name":"gl_BackSecondaryColor","type":"vec4","placeP":null,"versions":["130","140","150","330","400","410","420","430","440","450","460","130Core"],"stage":"vertex","requirements":null},
{"name":"gl_FogFragCoord","type":"float","placeP":null,"versions":["130","140","150","330","400","410","420","430","440","450","460","130Core"],"stage":"vertex","requirements":null},
{"name":"gl_PointCoord","type":"vec2","placeP":true,"versions":["110","120","130","140","150","330","400","410","420","430","440","450","460","110Core","120Core","130Core"],"stage":"fragment","requirements":null},
{"name":"gl_PointSize","type":"float","placeP":null,"versions":["110","120","130","140","150","330","400","410","420","430","440","450","460","110Core","120Core","130Core"],"stage":"vertex","requirements":null},
{"name":"gl_PointSize","type":"float","placeP":null,"versions":["130","140","150","330","400","410","420","430","440","450","460","130Core"],"stage":"geometry","requirements":null},
{"name":"gl_PointSize","type":"float","placeP":null,"versions":["400","410","420","430","440","450","460"],"stage":"tessellationEvaluation","requirements":null}]